single-cycle/Control_ROM.v
module Control_ROM(
    input [31:0] pcCurrent,
    input [2:0] opcode,
    input [31 : 0] instruction,

    output reg CONTROL_WRITE_REG,               // 1 = dest reg     0 = regB
    output reg CONTROL_WRITE_DATA,              // 1 = aluResult    0 = memResult
    output reg CONTROL_ENABLE_REG_WRITE,        // 1 = write register
    output reg CONTROL_ALUvalB,                 // 1 = regBvalue    0 = offsetExtended
    output reg [1:0] CONTROL_OPERATION,               // 1 = nor          0 = add
    output reg CONTROL_MEM_ACCESS,              // 1 = memory accessed
    output reg CONTROL_ENABLE_MEM_WRITE,        // 1 = write mem    0 = read mem
    output reg CONTROL_HALT,
    output reg CONTROL_JALR
);

    parameter OP_ADD = 3'b000;
    parameter OP_NOR = 3'b001;
    parameter OP_LW = 3'b010;
    parameter OP_SW = 3'b011;
    parameter OP_BEQ = 3'b100;
    parameter OP_JALR = 3'b101;
    parameter OP_HALT = 3'b110;
    parameter OP_NOOP = 3'b111;

    initial begin
        CONTROL_HALT <= 0;
        CONTROL_JALR <= 0;
        CONTROL_WRITE_REG <= 0;          // 1 = dest reg     0 = regB
        CONTROL_WRITE_DATA <= 0;         // 1 = aluResult    0 = memResult
        CONTROL_ENABLE_REG_WRITE <= 0;   // 1 = write register
        CONTROL_ALUvalB <= 0;            // 1 = regBvalue    0 = offsetExtended
        CONTROL_OPERATION <= 2'b00;          // 1 = nor          0 = add
        CONTROL_MEM_ACCESS <= 0;         // 1 = memory accessed
        CONTROL_ENABLE_MEM_WRITE <= 0;   // 1 = write mem    0 = read mem
    end

    always @(opcode) begin
        case(opcode)
            OP_ADD: begin
                CONTROL_HALT <= 0;
                CONTROL_JALR <= 0;
                CONTROL_WRITE_REG <= 1;          // 1 = dest reg
                CONTROL_WRITE_DATA <= 1;         // 1 = aluResult
                CONTROL_ENABLE_REG_WRITE <= 0;   // 0 = wait for ALU
                CONTROL_ALUvalB <= 1;            // 1 = regBvalue
                CONTROL_OPERATION <= 2'b00;          // 0 = add
                CONTROL_MEM_ACCESS <= 0;         // 0 = memory not accessed
                CONTROL_ENABLE_MEM_WRITE <= 0;   // 0 = read mem
            end
            OP_NOR: begin
                CONTROL_HALT <= 0;
                CONTROL_JALR <= 0;
                CONTROL_WRITE_REG <= 1;          // 1 = dest reg
                CONTROL_WRITE_DATA <= 1;         // 1 = aluResult 
                CONTROL_ENABLE_REG_WRITE <= 0;   // 0 = wait for ALU
                CONTROL_ALUvalB <= 1;            // 1 = regBvalue
                CONTROL_OPERATION <= 2'b01;          // 1 = nor
                CONTROL_MEM_ACCESS <= 0;         // 0 = memory not accessed
                CONTROL_ENABLE_MEM_WRITE <= 0;   // 0 = read mem
            end
            OP_LW: begin
                CONTROL_HALT <= 0;
                CONTROL_JALR <= 0;
                CONTROL_WRITE_REG <= 0;          // 0 = regB
                CONTROL_WRITE_DATA <= 0;         // 0 = memResult
                CONTROL_ALUvalB <= 0;            // 0 = offsetExtended
                CONTROL_ENABLE_REG_WRITE <= 1;   // 1 = write register
                CONTROL_OPERATION <= 2'b00;          // 0 = add
                CONTROL_MEM_ACCESS <= 1;         // 1 = memory accessed
                CONTROL_ENABLE_MEM_WRITE <= 0;   // 0 = read mem
            end
            OP_SW: begin
                CONTROL_HALT <= 0;
                CONTROL_JALR <= 0;
                CONTROL_WRITE_REG <= 0;          // 0 = regB
                CONTROL_WRITE_DATA <= 0;         // 0 = memResult
                CONTROL_ENABLE_REG_WRITE <= 0;   // 0 = don't write reg
                CONTROL_ALUvalB <= 0;            // 0 = offsetExtended
                CONTROL_OPERATION <= 2'b00;          // 0 = add
                CONTROL_MEM_ACCESS <= 1;         // 1 = memory accessed
                CONTROL_ENABLE_MEM_WRITE <= 1;   // 1 = write mem
            end
            OP_BEQ: begin
                CONTROL_HALT <= 0;
                CONTROL_JALR <= 0;
                CONTROL_WRITE_REG <= 0;          // 0 = regB
                CONTROL_WRITE_DATA <= 0;         // 0 = memResult
                CONTROL_ENABLE_REG_WRITE <= 0;   // 0 = don't write reg
                CONTROL_ALUvalB <= 1;            // 1 = regBvalue
                CONTROL_OPERATION <= 2'b10;          // 2 = equal?
                CONTROL_MEM_ACCESS <= 0;         // 0 = memory not accessed
                CONTROL_ENABLE_MEM_WRITE <= 0;   // 0 = read mem
            end
            OP_JALR: begin
                CONTROL_HALT <= 0;
                CONTROL_WRITE_REG <= 0;          // 0 = regB
                CONTROL_WRITE_DATA <= 2;         // 1 = pc+1
                CONTROL_ENABLE_REG_WRITE <= 1;   // 1 = write register
                CONTROL_JALR <= 1;               // 1 = jalr jump
                CONTROL_ALUvalB <= 0;            // 0 = offsetExtended
                CONTROL_OPERATION <= 2'b00;          // 0 = add
                CONTROL_MEM_ACCESS <= 0;         // 0 = memory not accessed
                CONTROL_ENABLE_MEM_WRITE <= 0;   // 0 = read mem
            end
            OP_HALT: begin
                CONTROL_HALT <= 1;
                CONTROL_JALR <= 0;
                CONTROL_WRITE_REG <= 0;          // 1 = dest reg     0 = regB
                CONTROL_WRITE_DATA <= 0;         // 1 = aluResult    0 = memResult
                CONTROL_ENABLE_REG_WRITE <= 0;   // 1 = write register
                CONTROL_ALUvalB <= 0;            // 1 = regBvalue    0 = offsetExtended
                CONTROL_OPERATION <= 2'b00;          // 1 = nor          0 = add
                CONTROL_MEM_ACCESS <= 0;         // 1 = memory accessed
                CONTROL_ENABLE_MEM_WRITE <= 0;   // 1 = write mem    0 = read mem
            end
            OP_NOOP: begin
                CONTROL_HALT <= 0;
                CONTROL_JALR <= 0;
                CONTROL_WRITE_REG <= 0;          // 1 = dest reg     0 = regB
                CONTROL_WRITE_DATA <= 0;         // 1 = aluResult    0 = memResult
                CONTROL_ENABLE_REG_WRITE <= 0;   // 1 = write register
                CONTROL_ALUvalB <= 0;            // 1 = regBvalue    0 = offsetExtended
                CONTROL_OPERATION <= 2'b00;          // 1 = nor          0 = add
                CONTROL_MEM_ACCESS <= 0;         // 1 = memory accessed
                CONTROL_ENABLE_MEM_WRITE <= 0;   // 1 = write mem    0 = read mem
            end
            default: begin
                CONTROL_ALUvalB <= 0;            // 1 = regBvalue
                CONTROL_HALT <= 0;
                CONTROL_JALR <= 0;
                CONTROL_WRITE_REG <= 0;          // 1 = dest reg
                CONTROL_WRITE_DATA <= 0;         // 1 = aluResult
                CONTROL_OPERATION <= 2'b00;          // 0 = add
                CONTROL_ENABLE_REG_WRITE <= 0;   // 1 = write register
                CONTROL_MEM_ACCESS <= 0;         // 0 = memory not accessed
                CONTROL_ENABLE_MEM_WRITE <= 0;
            end
        endcase
    end
endmodule

single-cycle/Data_Memory.v
module Data_Memory(
    input [31:0] aluResult,
    input [31:0] regBvalue,
    input CONTROL_MEM_ACCESS,               // 1 = accessed
    input CONTROL_ENABLE_MEM_WRITE,         // 1 = write, 0 = read
    input clk,
    
    output [31:0] memResult
);

    reg [63:0] Data[63:0];

    integer ii;

    initial begin
        for (ii = 0; ii < 64; ii = ii + 1) begin
            Data[ii] = 0;
        end

        // subone
        Data[12] = 1;
        Data[13] = 5;
        Data[14] = 2;
        Data[15] = 7;

        // jalrTest
        // Data[7] = 5;

    end

    always @(aluResult, regBvalue, CONTROL_MEM_ACCESS, CONTROL_ENABLE_MEM_WRITE) begin
            if (CONTROL_ENABLE_MEM_WRITE == 1) begin // write
                Data[aluResult] <= regBvalue;
            end
    end

    assign memResult = Data[aluResult];

endmodule

single-cycle/ALU.v
module ALU(
    input [31:0] aluValA,
    input [31:0] aluValB,
    input [1:0] CONTROL_OPERATION,            // 0 = ADD, 1 = NOR, 2 = EQUAL?
 
    output reg [31:0] aluResult,
    output reg CONTROL_BEQ
);

    always @ (aluValA, aluValB, CONTROL_OPERATION) begin
        case(CONTROL_OPERATION)
            2'b00: begin
                aluResult = aluValA + aluValB;
                CONTROL_BEQ = 0;
            end
            2'b01: begin
                aluResult = ~(aluValA | aluValB); 
                CONTROL_BEQ = 0;
            end
            2'b10: begin
                if (aluValA == aluValB) begin   // if equal, jump
                    CONTROL_BEQ = 1;
                end
                else begin
                    CONTROL_BEQ = 0;
                end
            end
        endcase
    end

endmodule

single-cycle/ALU_ValB_Mux.v
module ALU_ValB_Mux(
    input [31:0] offsetExtended,               // aluValB = 0
    input [31:0] regBvalue,                    // aluValB = 1
    input CONTROL_ALUvalB,
 
    output [31:0] aluValB
);

    assign aluValB = (CONTROL_ALUvalB == 1) ? regBvalue : offsetExtended;

endmodule

single-cycle/Reg_Memory.v
module Reg_Memory(
    input [2:0] read_regA,
    input [2:0] read_regB,
    input [2:0] write_reg,
    input [31:0] write_value,
    input CONTROL_ENABLE_REG_WRITE,
    input CONTROL_ALU_DONE,

    output reg [31:0] aluValA,
    output reg [31:0] regBvalue,
    output reg [31:0] reg1val
);

  reg [7:0] Register [31:0];

  integer ii;

  initial begin
      for (ii = 0; ii < 8; ii = ii + 1) begin
        Register[ii] = 0;
      end
  end

  always @(read_regA, read_regB, write_reg, write_value, CONTROL_ENABLE_REG_WRITE, CONTROL_ALU_DONE) begin
      if (CONTROL_ALU_DONE == 1) begin
        Register[write_reg] = write_value;
      end
      else begin
      aluValA <= Register[read_regA];
      regBvalue <= Register[read_regB]; 
        if (CONTROL_ENABLE_REG_WRITE == 1) begin
          Register[write_reg] = write_value;
        end
      end
      reg1val <= Register[1];
  end

endmodule


// add, nor 일때 reg A or B 가 destReg랑 같으면 오류.
// write value 계산이 아직 안되어서.. ALU쪽에서 CONTROL 하나 더 보내줘야할듯

single-cycle/Write_Reg_Mux.v
module Write_Reg_Mux(
    input [2:0] regB,               // writeReg = 0
    input [2:0] destReg,            // writeReg = 1
    input CONTROL_WRITE_REG,

    output reg [2:0] write_reg
);
 
    always @(CONTROL_WRITE_REG, destReg, regB) begin
        if (CONTROL_WRITE_REG == 1) begin   // use destReg
            write_reg <= destReg;
        end
        else begin
            write_reg <= regB;
        end
    end

endmodule

Write_Data_Mux.v
module Write_Data_Mux(
    input [31:0] memResult,                // writeData = 0 
    input [31:0] aluResult,                // writeData = 1
    input [31:0] pcPlusOne,                // writeData = 2
    input CONTROL_WRITE_DATA,

    output reg [31:0] write_value,
    output reg CONTROL_ALU_DONE

);

    always @(CONTROL_WRITE_DATA, memResult, aluResult, pcPlusOne) begin
        if (CONTROL_WRITE_DATA == 1) begin   // use aluResult
            write_value <= aluResult;
            CONTROL_ALU_DONE <= 1;
        end
        else if (CONTROL_WRITE_DATA == 0) begin
            write_value <= memResult;
            CONTROL_ALU_DONE <= 0;
        end
        else begin                      // jalr (save pc+1 to reg)
            write_value <= pcPlusOne;
            CONTROL_ALU_DONE <= 0;
        end
    end

endmodule

single-cycle/Instr_Memory.v
module Instr_Memory(
    input [31:0] pcCurrent,
    
    output [31:0] instr
);

    reg [31:0] Instruction[9:0];

    initial begin

        // subone
        Instruction[0] = 32'd8454154;
        Instruction[1] = 32'd8519691;
        Instruction[2] = 32'd8585225;
        Instruction[3] = 32'd17432578;
        Instruction[4] = 32'd720897;
        Instruction[5] = 32'd16842749;
        Instruction[6] = 32'd29360128;
        Instruction[7] = 32'd8454154;
        // Instruction[8] = 32'd16842746;
        Instruction[8] = 32'd25165824;


        // jalrTest
        // Instruction[0] = 32'd8519687;
        // Instruction[1] = 32'd22216704;
        // Instruction[2] = 32'd16777219;
        // Instruction[3] = 32'd29360128;
        // Instruction[4] = 32'd29360128;
        // Instruction[5] = 32'd1179649;
        // Instruction[6] = 32'd25165824;
    end

    assign instr = Instruction[pcCurrent];

endmodule

single-cycle/Program_Mux.v
module Program_Mux(
    input [31:0] pcCurrent,
    input [31:0] pcPlusOne,
    input CONTROL_BEQ,
    input [31:0] offsetExtended,
    input CONTROL_JALR,
    input [31:0] aluValA,

    output reg [31:0] pcOutput
); 
 
    always @(pcCurrent, CONTROL_BEQ, CONTROL_JALR) begin
        if (CONTROL_BEQ == 1) begin
            pcOutput = pcPlusOne + offsetExtended;
        end
        else if (CONTROL_JALR == 1) begin
            pcOutput = aluValA;
        end
        else begin
            pcOutput = pcPlusOne;
        end
    end
    
endmodule

single-cycle/Program_Counter.v
module Program_Counter(
  input clk,
  input [31:0] pcInput,
  input CONTROL_HALT,

  output reg [31:0] pcCurrent,
  output reg [31:0] pcPlusOne
);

  initial begin
    pcCurrent = 0;
    pcPlusOne = 1;
  end

  always @(posedge clk) begin
    if (CONTROL_HALT == 1) begin
      $finish;
    end
    else begin
      pcCurrent <= pcInput;
      pcPlusOne <= pcInput + 1;
    end
  end
  
endmodule

single-cycle/Clock.v
module Clock (
    output reg clk
);
 
    initial begin
        clk = 1;
    end

    always begin 
        #100 clk = ~clk;
    end

endmodule

single-cycle/CPU.v
/*

iverilog -o dsn ALU_ValB_Mux.v ALU.v Clock.V Control_ROM.v CPU.v Data_Memory.v Instr_Memory.v Program_Counter.v Program_Mux.v Reg_Memory.v Sign_Extend.v Write_Data_Mux.v Write_Reg_Mux.v

iverilog -o dsn top.v ALU_ValB_Mux.v ALU.v Clock.V Control_ROM.v CPU.v Data_Memory.v Instr_Memory.v Program_Counter.v Program_Mux.v Reg_Memory.v Sign_Extend.v Write_Data_Mux.v Write_Reg_Mux.v

vvp dsn

*/

module CPU(
    // input clk,
    // output [31:0] reg1out
);

    wire clk;
    wire [31:0] pcInput, pcCurrent, pcPlusOne;
    wire [31:0] offsetExtended;
    wire [31:0] write_value, aluValA, regBvalue, aluValB, aluResult;
    wire [2:0] write_reg;
    wire [31:0] memResult;

    wire [31 : 0] instruction;

    wire CONTROL_WRITE_REG, CONTROL_WRITE_DATA;
    wire CONTROL_ENABLE_REG_WRITE, CONTROL_ALUvalB, CONTROL_ALU_DONE;
    wire [1:0] CONTROL_OPERATION;
    wire CONTROL_MEM_ACCESS, CONTROL_ENABLE_MEM_WRITE;
    wire CONTROL_BEQ, CONTROL_JALR, CONTROL_HALT;

    Clock clock(
        .clk(clk)
    );

    Program_Counter PC(
        .clk(clk),
        .CONTROL_HALT(CONTROL_HALT),
        .pcInput(pcInput),
        .pcCurrent(pcCurrent),
        .pcPlusOne(pcPlusOne)
    );

    Program_Mux pM(
        .pcCurrent(pcCurrent),
        .pcPlusOne(pcPlusOne),
        .CONTROL_BEQ(CONTROL_BEQ),
        .offsetExtended(offsetExtended),
        .CONTROL_JALR(CONTROL_JALR),
        .aluValA(aluValA),
        .pcOutput(pcInput)
    );

    Instr_Memory instrM(
        .pcCurrent(pcCurrent),
        .instr(instruction)
    );

    Write_Data_Mux wdMux(
        .memResult(memResult),
        .aluResult(aluResult),
        .pcPlusOne(pcPlusOne),
        .CONTROL_ALU_DONE(CONTROL_ALU_DONE),
        .CONTROL_WRITE_DATA(CONTROL_WRITE_DATA),
        .write_value(write_value)
    );

    Write_Reg_Mux wrMux(
        .regB(instruction[18:16]),
        .destReg(instruction[2:0]),
        .CONTROL_WRITE_REG(CONTROL_WRITE_REG),
        .write_reg(write_reg)
    );

    // Sign_Extend sExtend(
    //     .offset(instruction[15:0]),
    //     .offsetExtended(offsetExtended)
    // );

    assign offsetExtended = { {16{instruction[15]}}, instruction[15:0] };

    wire [31:0] reg1val;
    Reg_Memory regM(
        .read_regA(instruction[21:19]),
        .read_regB(instruction[18:16]),
        .CONTROL_ALU_DONE(CONTROL_ALU_DONE),
        .write_reg(write_reg),
        .write_value(write_value),
        .CONTROL_ENABLE_REG_WRITE(CONTROL_ENABLE_REG_WRITE),
        .aluValA(aluValA),
        .regBvalue(regBvalue),
        .reg1val(reg1val)
    );

    ALU_ValB_Mux vbMux(
        .offsetExtended(offsetExtended),
        .regBvalue(regBvalue),
        .CONTROL_ALUvalB(CONTROL_ALUvalB),
        .aluValB(aluValB)
    );

    ALU alu(
        .aluValA(aluValA),
        .aluValB(aluValB),
        .CONTROL_OPERATION(CONTROL_OPERATION),
        .aluResult(aluResult),
        .CONTROL_BEQ(CONTROL_BEQ)
    );

    Data_Memory dataM(
        .aluResult(aluResult),
        .regBvalue(regBvalue),
        .CONTROL_MEM_ACCESS(CONTROL_MEM_ACCESS),
        .CONTROL_ENABLE_MEM_WRITE(CONTROL_ENABLE_MEM_WRITE),
        .clk(clk),
        .memResult(memResult)
    );

    Control_ROM cRom(
        .pcCurrent(pcCurrent),
        .opcode(instruction[24:22]),
        .instruction(instruction),
        .CONTROL_WRITE_REG(CONTROL_WRITE_REG),
        .CONTROL_WRITE_DATA(CONTROL_WRITE_DATA),
        .CONTROL_ENABLE_REG_WRITE(CONTROL_ENABLE_REG_WRITE),
        .CONTROL_ALUvalB(CONTROL_ALUvalB),
        .CONTROL_OPERATION(CONTROL_OPERATION),
        .CONTROL_MEM_ACCESS(CONTROL_MEM_ACCESS),
        .CONTROL_ENABLE_MEM_WRITE(CONTROL_ENABLE_MEM_WRITE),
        .CONTROL_HALT(CONTROL_HALT),
        .CONTROL_JALR(CONTROL_JALR)
    );

    // assign reg1out = reg1val;


    // Running simulation via iverilog
    initial begin
        $dumpfile("test.vcd");
        $dumpvars(0,CPU);
    end

    reg [32:0] curOpcode = "ADD";

    always @(instruction[24:22]) begin
        case(instruction[24:22]) 
            3'b000:
                curOpcode = "ADD";
            3'b001:
                curOpcode = "NOR";
            3'b010:
                curOpcode = "LW";
            3'b011:
                curOpcode = "SW";
            3'b100:
                curOpcode = "BEQ";
            3'b101:
                curOpcode = "JALR";
            3'b110:
                curOpcode = "HALT";
            3'b111:
                curOpcode = "NOOP";
        endcase
    end

    initial
        $monitor("At time %t, pcCurrent = %0d, instruction = %s, reg1 value = %0d",
            $time, pcCurrent, curOpcode, reg1val);

endmodule

single-cycle/test.vcd
$date
	Sat Jun 29 22:02:47 2024
$end
$version
	Icarus Verilog
$end
$timescale
	1s
$end
$scope module CPU $end
$var wire 32 ! write_value [31:0] $end
$var wire 3 " write_reg [2:0] $end
$var wire 32 # regBvalue [31:0] $end
$var wire 32 $ reg1val [31:0] $end
$var wire 32 % pcPlusOne [31:0] $end
$var wire 32 & pcInput [31:0] $end
$var wire 32 ' pcCurrent [31:0] $end
$var wire 32 ( offsetExtended [31:0] $end
$var wire 32 ) memResult [31:0] $end
$var wire 32 * instruction [31:0] $end
$var wire 1 + clk $end
$var wire 32 , aluValB [31:0] $end
$var wire 32 - aluValA [31:0] $end
$var wire 32 . aluResult [31:0] $end
$var wire 1 / CONTROL_WRITE_REG $end
$var wire 1 0 CONTROL_WRITE_DATA $end
$var wire 2 1 CONTROL_OPERATION [1:0] $end
$var wire 1 2 CONTROL_MEM_ACCESS $end
$var wire 1 3 CONTROL_JALR $end
$var wire 1 4 CONTROL_HALT $end
$var wire 1 5 CONTROL_ENABLE_REG_WRITE $end
$var wire 1 6 CONTROL_ENABLE_MEM_WRITE $end
$var wire 1 7 CONTROL_BEQ $end
$var wire 1 8 CONTROL_ALUvalB $end
$var wire 1 9 CONTROL_ALU_DONE $end
$var reg 33 : curOpcode [32:0] $end
$scope module PC $end
$var wire 32 ; pcInput [31:0] $end
$var wire 1 + clk $end
$var wire 1 4 CONTROL_HALT $end
$var reg 32 < pcCurrent [31:0] $end
$var reg 32 = pcPlusOne [31:0] $end
$upscope $end
$scope module alu $end
$var wire 32 > aluValB [31:0] $end
$var wire 32 ? aluValA [31:0] $end
$var wire 2 @ CONTROL_OPERATION [1:0] $end
$var reg 1 7 CONTROL_BEQ $end
$var reg 32 A aluResult [31:0] $end
$upscope $end
$scope module cRom $end
$var wire 3 B opcode [2:0] $end
$var wire 32 C pcCurrent [31:0] $end
$var wire 32 D instruction [31:0] $end
$var parameter 3 E OP_ADD $end
$var parameter 3 F OP_BEQ $end
$var parameter 3 G OP_HALT $end
$var parameter 3 H OP_JALR $end
$var parameter 3 I OP_LW $end
$var parameter 3 J OP_NOOP $end
$var parameter 3 K OP_NOR $end
$var parameter 3 L OP_SW $end
$var reg 1 8 CONTROL_ALUvalB $end
$var reg 1 6 CONTROL_ENABLE_MEM_WRITE $end
$var reg 1 5 CONTROL_ENABLE_REG_WRITE $end
$var reg 1 4 CONTROL_HALT $end
$var reg 1 3 CONTROL_JALR $end
$var reg 1 2 CONTROL_MEM_ACCESS $end
$var reg 2 M CONTROL_OPERATION [1:0] $end
$var reg 1 0 CONTROL_WRITE_DATA $end
$var reg 1 / CONTROL_WRITE_REG $end
$upscope $end
$scope module clock $end
$var reg 1 + clk $end
$upscope $end
$scope module dataM $end
$var wire 1 6 CONTROL_ENABLE_MEM_WRITE $end
$var wire 1 2 CONTROL_MEM_ACCESS $end
$var wire 32 N aluResult [31:0] $end
$var wire 1 + clk $end
$var wire 32 O regBvalue [31:0] $end
$var wire 32 P memResult [31:0] $end
$var integer 32 Q ii [31:0] $end
$upscope $end
$scope module instrM $end
$var wire 32 R instr [31:0] $end
$var wire 32 S pcCurrent [31:0] $end
$upscope $end
$scope module pM $end
$var wire 1 7 CONTROL_BEQ $end
$var wire 1 3 CONTROL_JALR $end
$var wire 32 T offsetExtended [31:0] $end
$var wire 32 U pcCurrent [31:0] $end
$var wire 32 V pcPlusOne [31:0] $end
$var wire 32 W aluValA [31:0] $end
$var reg 32 X pcOutput [31:0] $end
$upscope $end
$scope module regM $end
$var wire 1 5 CONTROL_ENABLE_REG_WRITE $end
$var wire 3 Y read_regA [2:0] $end
$var wire 3 Z read_regB [2:0] $end
$var wire 32 [ write_value [31:0] $end
$var wire 3 \ write_reg [2:0] $end
$var wire 1 9 CONTROL_ALU_DONE $end
$var reg 32 ] aluValA [31:0] $end
$var reg 32 ^ reg1val [31:0] $end
$var reg 32 _ regBvalue [31:0] $end
$var integer 32 ` ii [31:0] $end
$upscope $end
$scope module vbMux $end
$var wire 1 8 CONTROL_ALUvalB $end
$var wire 32 a offsetExtended [31:0] $end
$var wire 32 b regBvalue [31:0] $end
$var wire 32 c aluValB [31:0] $end
$upscope $end
$scope module wdMux $end
$var wire 1 0 CONTROL_WRITE_DATA $end
$var wire 32 d aluResult [31:0] $end
$var wire 32 e memResult [31:0] $end
$var wire 32 f pcPlusOne [31:0] $end
$var reg 1 9 CONTROL_ALU_DONE $end
$var reg 32 g write_value [31:0] $end
$upscope $end
$scope module wrMux $end
$var wire 1 / CONTROL_WRITE_REG $end
$var wire 3 h destReg [2:0] $end
$var wire 3 i regB [2:0] $end
$var reg 3 j write_reg [2:0] $end
$upscope $end
$upscope $end
$enddefinitions $end
$comment Show the parameter values. $end
$dumpall
b11 L
b1 K
b111 J
b10 I
b101 H
b110 G
b100 F
b0 E
$end
#0
$dumpvars
b1 j
b1 i
b110 h
b10 g
b1 f
b10 e
b1110 d
b1110 c
b1 b
b1110 a
b1000 `
b1 _
b10 ^
b0 ]
b1 \
b10 [
b1 Z
b0 Y
b1 X
b0 W
b1 V
b0 U
b1110 T
b0 S
b100000010000000000001110 R
b1000000 Q
b10 P
b1 O
b1110 N
b0 M
b100000010000000000001110 D
b0 C
b10 B
b1110 A
b0 @
b0 ?
b1110 >
b1 =
b0 <
b1 ;
b100110001010111 :
09
08
07
06
15
04
03
12
b0 1
00
0/
b1110 .
b0 -
b1110 ,
1+
b100000010000000000001110 *
b10 )
b1110 (
b0 '
b1 &
b1 %
b10 $
b1 #
b1 "
b10 !
$end
#100
0+
#200
b101 !
b101 [
b101 g
b0 #
b0 O
b0 _
b0 b
b10 "
b10 \
b10 j
b101 )
b101 P
b101 e
b1101 .
b1101 A
b1101 N
b1101 d
b1101 ,
b1101 >
b1101 c
b10 Z
b1101 (
b1101 T
b1101 a
b101 h
b10 i
b10 &
b10 ;
b10 X
b10 %
b10 =
b10 V
b10 f
b100000100000000000001101 *
b100000100000000000001101 D
b100000100000000000001101 R
b1 '
b1 <
b1 C
b1 S
b1 U
1+
#300
0+
#400
b1 !
b1 [
b1 g
b11 "
b11 \
b11 j
b1 )
b1 P
b1 e
b1100 .
b1100 A
b1100 N
b1100 d
b1100 ,
b1100 >
b1100 c
b11 Z
b1100 (
b1100 T
b1100 a
b100 h
b11 i
b11 &
b11 ;
b11 X
b11 %
b11 =
b11 V
b11 f
b100000110000000000001100 *
b100000110000000000001100 D
b100000110000000000001100 R
b10 '
b10 <
b10 C
b10 S
b10 U
1+
#500
0+
#600
07
b0 !
b0 [
b0 g
02
b10 1
b10 @
b10 M
18
05
b101 #
b101 O
b101 _
b101 b
b10 -
b10 ?
b10 W
b10 ]
b10 "
b10 \
b10 j
b0 )
b0 P
b0 e
b10 .
b10 A
b10 N
b10 d
b10000100100010101010001 :
b101 ,
b101 >
b101 c
b100 B
b10 Z
b1 Y
b10 (
b10 T
b10 a
b10 h
b10 i
b100 &
b100 ;
b100 X
b100 %
b100 =
b100 V
b100 f
b1000010100000000000000010 *
b1000010100000000000000010 D
b1000010100000000000000010 R
b11 '
b11 <
b11 C
b11 S
b11 U
1+
#700
0+
#800
b11 $
b11 ^
19
b11 !
b11 [
b11 g
b11 .
b11 A
b11 N
b11 d
b1 ,
b1 >
b1 c
b0 1
b0 @
b0 M
10
1/
b1 #
b1 O
b1 _
b1 b
b1 "
b1 \
b1 j
b10000010100010001000100 :
b0 B
b11 Z
b1 (
b1 T
b1 a
b1 h
b11 i
b101 &
b101 ;
b101 X
b101 %
b101 =
b101 V
b101 f
b10110000000000000001 *
b10110000000000000001 D
b10110000000000000001 R
b100 '
b100 <
b100 C
b100 S
b100 U
1+
#900
0+
#1000
17
b0 ,
b0 >
b0 c
b0 #
b0 O
b0 _
b0 b
b0 -
b0 ?
b0 W
b0 ]
09
b0 !
b0 [
b0 g
b10 1
b10 @
b10 M
00
0/
b0 "
b0 \
b0 j
b10000100100010101010001 :
b100 B
b0 Z
b0 Y
b11111111111111111111111111111101 (
b11111111111111111111111111111101 T
b11111111111111111111111111111101 a
b101 h
b0 i
b11 &
b11 ;
b11 X
b110 %
b110 =
b110 V
b110 f
b1000000001111111111111101 *
b1000000001111111111111101 D
b1000000001111111111111101 R
b101 '
b101 <
b101 C
b101 S
b101 U
1+
#1100
0+
#1200
b101 ,
b101 >
b101 c
07
b101 #
b101 O
b101 _
b101 b
b11 -
b11 ?
b11 W
b11 ]
b10 "
b10 \
b10 j
b10 Z
b1 Y
b10 (
b10 T
b10 a
b10 h
b10 i
b100 &
b100 ;
b100 X
b100 %
b100 =
b100 V
b100 f
b1000010100000000000000010 *
b1000010100000000000000010 D
b1000010100000000000000010 R
b11 '
b11 <
b11 C
b11 S
b11 U
1+
#1300
0+
#1400
b100 $
b100 ^
19
b100 !
b100 [
b100 g
b100 .
b100 A
b100 N
b100 d
b1 ,
b1 >
b1 c
b0 1
b0 @
b0 M
10
1/
b1 #
b1 O
b1 _
b1 b
b1 "
b1 \
b1 j
b10000010100010001000100 :
b0 B
b11 Z
b1 (
b1 T
b1 a
b1 h
b11 i
b101 &
b101 ;
b101 X
b101 %
b101 =
b101 V
b101 f
b10110000000000000001 *
b10110000000000000001 D
b10110000000000000001 R
b100 '
b100 <
b100 C
b100 S
b100 U
1+
#1500
0+
#1600
17
b0 ,
b0 >
b0 c
b0 #
b0 O
b0 _
b0 b
b0 -
b0 ?
b0 W
b0 ]
09
b0 !
b0 [
b0 g
b10 1
b10 @
b10 M
00
0/
b0 "
b0 \
b0 j
b10000100100010101010001 :
b100 B
b0 Z
b0 Y
b11111111111111111111111111111101 (
b11111111111111111111111111111101 T
b11111111111111111111111111111101 a
b101 h
b0 i
b11 &
b11 ;
b11 X
b110 %
b110 =
b110 V
b110 f
b1000000001111111111111101 *
b1000000001111111111111101 D
b1000000001111111111111101 R
b101 '
b101 <
b101 C
b101 S
b101 U
1+
#1700
0+
#1800
b101 ,
b101 >
b101 c
07
b101 #
b101 O
b101 _
b101 b
b100 -
b100 ?
b100 W
b100 ]
b10 "
b10 \
b10 j
b10 Z
b1 Y
b10 (
b10 T
b10 a
b10 h
b10 i
b100 &
b100 ;
b100 X
b100 %
b100 =
b100 V
b100 f
b1000010100000000000000010 *
b1000010100000000000000010 D
b1000010100000000000000010 R
b11 '
b11 <
b11 C
b11 S
b11 U
1+
#1900
0+
#2000
b101 $
b101 ^
19
b101 !
b101 [
b101 g
b101 .
b101 A
b101 N
b101 d
b1 ,
b1 >
b1 c
b0 1
b0 @
b0 M
10
1/
b1 #
b1 O
b1 _
b1 b
b1 "
b1 \
b1 j
b10000010100010001000100 :
b0 B
b11 Z
b1 (
b1 T
b1 a
b1 h
b11 i
b101 &
b101 ;
b101 X
b101 %
b101 =
b101 V
b101 f
b10110000000000000001 *
b10110000000000000001 D
b10110000000000000001 R
b100 '
b100 <
b100 C
b100 S
b100 U
1+
#2100
0+
#2200
17
b0 ,
b0 >
b0 c
b0 #
b0 O
b0 _
b0 b
b0 -
b0 ?
b0 W
b0 ]
09
b0 !
b0 [
b0 g
b10 1
b10 @
b10 M
00
0/
b0 "
b0 \
b0 j
b10000100100010101010001 :
b100 B
b0 Z
b0 Y
b11111111111111111111111111111101 (
b11111111111111111111111111111101 T
b11111111111111111111111111111101 a
b101 h
b0 i
b11 &
b11 ;
b11 X
b110 %
b110 =
b110 V
b110 f
b1000000001111111111111101 *
b1000000001111111111111101 D
b1000000001111111111111101 R
b101 '
b101 <
b101 C
b101 S
b101 U
1+
#2300
0+
#2400
b101 ,
b101 >
b101 c
17
b101 #
b101 O
b101 _
b101 b
b101 -
b101 ?
b101 W
b101 ]
b10 "
b10 \
b10 j
b10 Z
b1 Y
b10 (
b10 T
b10 a
b10 h
b10 i
b110 &
b110 ;
b110 X
b100 %
b100 =
b100 V
b100 f
b1000010100000000000000010 *
b1000010100000000000000010 D
b1000010100000000000000010 R
b11 '
b11 <
b11 C
b11 S
b11 U
1+
#2500
0+
